{
  "acoustic_entropy": 107.93882751464844,
  "bands": [
    {
      "high_freq": 148.1999969482422,
      "loudness": -54.61054229736328,
      "loudness_range": 33.27376937866211,
      "mid_mean": -56.03250503540039,
      "mid_to_side_loudness": 0,
      "mid_to_side_loudness_range": 0,
      "side_mean": -70
    },
    {
      "high_freq": 392.3793640136719,
      "loudness": -44.523128509521484,
      "loudness_range": 30.991924285888672,
      "low_freq": 148.1999969482422,
      "mid_mean": -41.79742431640625,
      "mid_to_side_loudness": 0,
      "mid_to_side_loudness_range": 0,
      "side_mean": -70
    },
    {
      "high_freq": 794.6976318359375,
      "loudness": -48.420040130615234,
      "loudness_range": 26.90009880065918,
      "low_freq": 392.3793640136719,
      "mid_mean": -48.89491271972656,
      "mid_to_side_loudness": 0,
      "mid_to_side_loudness_range": 0,
      "side_mean": -70
    },
    {
      "high_freq": 1457.5709228515625,
      "loudness": -40.45183181762695,
      "loudness_range": 25.223758697509766,
      "low_freq": 794.6976318359375,
      "mid_mean": -38.03902816772461,
      "mid_to_side_loudness": 0,
      "mid_to_side_loudness_range": 0,
      "side_mean": -70
    },
    {
      "high_freq": 2549.74365234375,
      "loudness": -42.79412078857422,
      "loudness_range": 26.289546966552734,
      "low_freq": 1457.5709228515625,
      "mid_mean": -39.88655471801758,
      "mid_to_side_loudness": 0,
      "mid_to_side_loudness_range": 0,
      "side_mean": -70
    },
    {
      "high_freq": 4349.24462890625,
      "loudness": -49.62458038330078,
      "loudness_range": 20.06808853149414,
      "low_freq": 2549.74365234375,
      "mid_mean": -50.802452087402344,
      "mid_to_side_loudness": 0,
      "mid_to_side_loudness_range": 0,
      "side_mean": -70
    },
    {
      "high_freq": 7314.1640625,
      "loudness": -46.295677185058594,
      "loudness_range": 16.77695083618164,
      "low_freq": 4349.24462890625,
      "mid_mean": -48.23267364501953,
      "mid_to_side_loudness": 0,
      "mid_to_side_loudness_range": 0,
      "side_mean": -70
    },
    {
      "high_freq": 12199.2666015625,
      "loudness": -54.79705810546875,
      "loudness_range": 18.580642700195312,
      "low_freq": 7314.1640625,
      "mid_mean": -55.30165481567383,
      "mid_to_side_loudness": 0,
      "mid_to_side_loudness_range": 0,
      "side_mean": -70
    },
    {
      "loudness": -62.32707595825195,
      "loudness_range": 21.105117797851562,
      "low_freq": 12199.2666015625,
      "mid_mean": -60.11733627319336,
      "mid_to_side_loudness": 0,
      "mid_to_side_loudness_range": 0,
      "side_mean": -70
    }
  ],
  "bands_short": [
    {
      "high_freq": 148.1999969482422,
      "loudness": -64.0791244506836,
      "loudness_range": 30.45063018798828,
      "mid_mean": -64.07100677490234,
      "mid_to_side_loudness": 0,
      "mid_to_side_loudness_range": 0,
      "side_mean": -70
    },
    {
      "high_freq": 392.3793640136719,
      "loudness": -48.13127899169922,
      "loudness_range": 35.85443115234375,
      "low_freq": 148.1999969482422,
      "mid_mean": -52.2784423828125,
      "mid_to_side_loudness": 0,
      "mid_to_side_loudness_range": 0,
      "side_mean": -70
    },
    {
      "high_freq": 794.6976318359375,
      "loudness": -50.62297821044922,
      "loudness_range": 28.650596618652344,
      "low_freq": 392.3793640136719,
      "mid_mean": -53.513206481933594,
      "mid_to_side_loudness": 0,
      "mid_to_side_loudness_range": 0,
      "side_mean": -70
    },
    {
      "high_freq": 1457.5709228515625,
      "loudness": -42.711891174316406,
      "loudness_range": 30.53782844543457,
      "low_freq": 794.6976318359375,
      "mid_mean": -44.25596237182617,
      "mid_to_side_loudness": 0,
      "mid_to_side_loudness_range": 0,
      "side_mean": -70
    },
    {
      "high_freq": 2549.74365234375,
      "loudness": -43.917850494384766,
      "loudness_range": 30.435819625854492,
      "low_freq": 1457.5709228515625,
      "mid_mean": -49.33467102050781,
      "mid_to_side_loudness": 0,
      "mid_to_side_loudness_range": 0,
      "side_mean": -70
    },
    {
      "high_freq": 4349.24462890625,
      "loudness": -51.14719772338867,
      "loudness_range": 25.077205657958984,
      "low_freq": 2549.74365234375,
      "mid_mean": -53.935550689697266,
      "mid_to_side_loudness": 0,
      "mid_to_side_loudness_range": 0,
      "side_mean": -70
    },
    {
      "high_freq": 7314.1640625,
      "loudness": -46.462501525878906,
      "loudness_range": 19.878387451171875,
      "low_freq": 4349.24462890625,
      "mid_mean": -52.13916015625,
      "mid_to_side_loudness": 0,
      "mid_to_side_loudness_range": 0,
      "side_mean": -70
    },
    {
      "high_freq": 12199.2666015625,
      "loudness": -55.45047378540039,
      "loudness_range": 23.15386962890625,
      "low_freq": 7314.1640625,
      "mid_mean": -57.51939010620117,
      "mid_to_side_loudness": 0,
      "mid_to_side_loudness_range": 0,
      "side_mean": -70
    },
    {
      "loudness": -63.949954986572266,
      "loudness_range": 25.86014175415039,
      "low_freq": 12199.2666015625,
      "mid_mean": -62.110958099365234,
      "mid_to_side_loudness": 0,
      "mid_to_side_loudness_range": 0,
      "side_mean": -70
    }
  ],
  "bandwidth": 805.972412109375,
  "channels": 2,
  "covariance": [
    [
      148.4097137451172,
      0,
      118.92570495605469,
      0,
      127.68704223632812,
      0,
      86.90382385253906,
      0,
      70.12570190429688,
      0,
      91.76345825195312,
      0,
      97.17530822753906,
      0,
      82.68148040771484,
      0,
      53.095027923583984,
      0
    ],
    [
      0,
      0,
      0,
      0,
      0,
      0,
      0,
      0,
      0,
      0,
      0,
      0,
      0,
      0,
      0,
      0,
      0,
      0
    ],
    [
      118.92570495605469,
      0,
      120.51952362060547,
      0,
      86.32530212402344,
      0,
      86.79827880859375,
      0,
      71.5051498413086,
      0,
      38.806129455566406,
      0,
      45.40070724487305,
      0,
      45.56098556518555,
      0,
      26.233837127685547,
      0
    ],
    [
      0,
      0,
      0,
      0,
      0,
      0,
      0,
      0,
      0,
      0,
      0,
      0,
      0,
      0,
      0,
      0,
      0,
      0
    ],
    [
      127.68704223632812,
      0,
      86.32530212402344,
      0,
      137.9959259033203,
      0,
      68.34558868408203,
      0,
      46.054988861083984,
      0,
      99.6132583618164,
      0,
      109.431396484375,
      0,
      85.51912689208984,
      0,
      55.818782806396484,
      0
    ],
    [
      0,
      0,
      0,
      0,
      0,
      0,
      0,
      0,
      0,
      0,
      0,
      0,
      0,
      0,
      0,
      0,
      0,
      0
    ],
    [
      86.90382385253906,
      0,
      86.79827880859375,
      0,
      68.34558868408203,
      0,
      111.27584838867188,
      0,
      40.21840286254883,
      0,
      12.285773277282715,
      0,
      24.346420288085938,
      0,
      33.929412841796875,
      0,
      6.781213283538818,
      0
    ],
    [
      0,
      0,
      0,
      0,
      0,
      0,
      0,
      0,
      0,
      0,
      0,
      0,
      0,
      0,
      0,
      0,
      0,
      0
    ],
    [
      70.12570190429688,
      0,
      71.5051498413086,
      0,
      46.054988861083984,
      0,
      40.21840286254883,
      0,
      84.56055450439453,
      0,
      46.751487731933594,
      0,
      51.49278259277344,
      0,
      45.01614761352539,
      0,
      36.786643981933594,
      0
    ],
    [
      0,
      0,
      0,
      0,
      0,
      0,
      0,
      0,
      0,
      0,
      0,
      0,
      0,
      0,
      0,
      0,
      0,
      0
    ],
    [
      91.76345825195312,
      0,
      38.806129455566406,
      0,
      99.6132583618164,
      0,
      12.285773277282715,
      0,
      46.751487731933594,
      0,
      123.95537567138672,
      0,
      123.31034851074219,
      0,
      96.09430694580078,
      0,
      77.91362762451172,
      0
    ],
    [
      0,
      0,
      0,
      0,
      0,
      0,
      0,
      0,
      0,
      0,
      0,
      0,
      0,
      0,
      0,
      0,
      0,
      0
    ],
    [
      97.17530822753906,
      0,
      45.40070724487305,
      0,
      109.431396484375,
      0,
      24.346420288085938,
      0,
      51.49278259277344,
      0,
      123.31034851074219,
      0,
      143.61570739746094,
      0,
      100.83658599853516,
      0,
      78.74205780029297,
      0
    ],
    [
      0,
      0,
      0,
      0,
      0,
      0,
      0,
      0,
      0,
      0,
      0,
      0,
      0,
      0,
      0,
      0,
      0,
      0
    ],
    [
      82.68148040771484,
      0,
      45.56098556518555,
      0,
      85.51912689208984,
      0,
      33.929412841796875,
      0,
      45.01614761352539,
      0,
      96.09430694580078,
      0,
      100.83658599853516,
      0,
      85.50592041015625,
      0,
      61.628963470458984,
      0
    ],
    [
      0,
      0,
      0,
      0,
      0,
      0,
      0,
      0,
      0,
      0,
      0,
      0,
      0,
      0,
      0,
      0,
      0,
      0
    ],
    [
      53.095027923583984,
      0,
      26.233837127685547,
      0,
      55.818782806396484,
      0,
      6.781213283538818,
      0,
      36.786643981933594,
      0,
      77.91362762451172,
      0,
      78.74205780029297,
      0,
      61.628963470458984,
      0,
      55.558128356933594,
      0
    ],
    [
      0,
      0,
      0,
      0,
      0,
      0,
      0,
      0,
      0,
      0,
      0,
      0,
      0,
      0,
      0,
      0,
      0,
      0
    ]
  ],
  "covariance_short": [
    [
      69.3768081665039,
      0,
      102.89212799072266,
      0,
      79.8404769897461,
      0,
      79.2259292602539,
      0,
      86.64999389648438,
      0,
      58.98691940307617,
      0,
      65.95816040039062,
      0,
      51.203948974609375,
      0,
      30.83483123779297,
      0
    ],
    [
      0,
      0,
      0,
      0,
      0,
      0,
      0,
      0,
      0,
      0,
      0,
      0,
      0,
      0,
      0,
      0,
      0,
      0
    ],
    [
      102.89212799072266,
      0,
      202.66123962402344,
      0,
      169.96124267578125,
      0,
      161.61026000976562,
      0,
      190.60792541503906,
      0,
      137.95069885253906,
      0,
      155.91433715820312,
      0,
      115.16800689697266,
      0,
      71.77639770507812,
      0
    ],
    [
      0,
      0,
      0,
      0,
      0,
      0,
      0,
      0,
      0,
      0,
      0,
      0,
      0,
      0,
      0,
      0,
      0,
      0
    ],
    [
      79.8404769897461,
      0,
      169.96124267578125,
      0,
      158.72665405273438,
      0,
      145.50828552246094,
      0,
      166.4278106689453,
      0,
      125.25862884521484,
      0,
      139.10122680664062,
      0,
      103.55318450927734,
      0,
      65.44024658203125,
      0
    ],
    [
      0,
      0,
      0,
      0,
      0,
      0,
      0,
      0,
      0,
      0,
      0,
      0,
      0,
      0,
      0,
      0,
      0,
      0
    ],
    [
      79.2259292602539,
      0,
      161.61026000976562,
      0,
      145.50828552246094,
      0,
      213.9960479736328,
      0,
      144.81185913085938,
      0,
      95.75398254394531,
      0,
      119.75965881347656,
      0,
      94.99139404296875,
      0,
      45.806339263916016,
      0
    ],
    [
      0,
      0,
      0,
      0,
      0,
      0,
      0,
      0,
      0,
      0,
      0,
      0,
      0,
      0,
      0,
      0,
      0,
      0
    ],
    [
      86.64999389648438,
      0,
      190.60792541503906,
      0,
      166.4278106689453,
      0,
      144.81185913085938,
      0,
      234.32899475097656,
      0,
      163.4052734375,
      0,
      181.75860595703125,
      0,
      131.97454833984375,
      0,
      89.97222137451172,
      0
    ],
    [
      0,
      0,
      0,
      0,
      0,
      0,
      0,
      0,
      0,
      0,
      0,
      0,
      0,
      0,
      0,
      0,
      0,
      0
    ],
    [
      58.98691940307617,
      0,
      137.95069885253906,
      0,
      125.25862884521484,
      0,
      95.75398254394531,
      0,
      163.4052734375,
      0,
      141.63140869140625,
      0,
      150.5310516357422,
      0,
      110.42972564697266,
      0,
      82.28904724121094,
      0
    ],
    [
      0,
      0,
      0,
      0,
      0,
      0,
      0,
      0,
      0,
      0,
      0,
      0,
      0,
      0,
      0,
      0,
      0,
      0
    ],
    [
      65.95816040039062,
      0,
      155.91433715820312,
      0,
      139.10122680664062,
      0,
      119.75965881347656,
      0,
      181.75860595703125,
      0,
      150.5310516357422,
      0,
      178.6452178955078,
      0,
      124.67101287841797,
      0,
      89.1290512084961,
      0
    ],
    [
      0,
      0,
      0,
      0,
      0,
      0,
      0,
      0,
      0,
      0,
      0,
      0,
      0,
      0,
      0,
      0,
      0,
      0
    ],
    [
      51.203948974609375,
      0,
      115.16800689697266,
      0,
      103.55318450927734,
      0,
      94.99139404296875,
      0,
      131.97454833984375,
      0,
      110.42972564697266,
      0,
      124.67101287841797,
      0,
      99.70571899414062,
      0,
      68.65111541748047,
      0
    ],
    [
      0,
      0,
      0,
      0,
      0,
      0,
      0,
      0,
      0,
      0,
      0,
      0,
      0,
      0,
      0,
      0,
      0,
      0
    ],
    [
      30.83483123779297,
      0,
      71.77639770507812,
      0,
      65.44024658203125,
      0,
      45.806339263916016,
      0,
      89.97222137451172,
      0,
      82.28904724121094,
      0,
      89.1290512084961,
      0,
      68.65111541748047,
      0,
      59.8447380065918,
      0
    ],
    [
      0,
      0,
      0,
      0,
      0,
      0,
      0,
      0,
      0,
      0,
      0,
      0,
      0,
      0,
      0,
      0,
      0,
      0
    ]
  ],
  "damage": -21.532201766967773,
  "diff_bandwidth": 785.9933471679688,
  "dissonance": 10.866864922561527,
  "drr": 2.837857723236084,
  "dynamics": 6.824929714202881,
  "format": 1245190,
  "frames": 498624,
  "loudness": -29.200002670288086,
  "loudness_range": 20.713619232177734,
  "loudness_range_short": 33.917823791503906,
  "lowpass_true_peak_15khz": -3.890631914138794,
  "mastering3_acoustic_entropies": [
    {
      "acoustic_entropy": 8.468067169189453,
      "acoustic_entropy_mono": 8.468067169189453,
      "band_eliminated_acoustic_entropies": [
        {
          "acoustic_entropy": 8.465734481811523,
          "acoustic_entropy_side": 8.468067169189453,
          "hz": 129.47220167065723
        },
        {
          "acoustic_entropy": 8.363729476928711,
          "acoustic_entropy_side": 8.468067169189453,
          "hz": 202.92927478742237
        },
        {
          "acoustic_entropy": 8.296163558959961,
          "acoustic_entropy_side": 8.468067169189453,
          "hz": 282.89161906338205
        },
        {
          "acoustic_entropy": 8.314474105834961,
          "acoustic_entropy_side": 8.468067169189453,
          "hz": 369.9353335868758
        },
        {
          "acoustic_entropy": 8.296257972717285,
          "acoustic_entropy_side": 8.468067169189453,
          "hz": 464.6875360973435
        },
        {
          "acoustic_entropy": 8.345303535461426,
          "acoustic_entropy_side": 8.468067169189453,
          "hz": 567.8308811364784
        },
        {
          "acoustic_entropy": 8.328174591064453,
          "acoustic_entropy_side": 8.468067169189453,
          "hz": 680.1084783214808
        },
        {
          "acoustic_entropy": 8.468515396118164,
          "acoustic_entropy_side": 8.468067169189453,
          "hz": 802.3292461747484
        },
        {
          "acoustic_entropy": 8.605518341064453,
          "acoustic_entropy_side": 8.468067169189453,
          "hz": 935.3737400823702
        },
        {
          "acoustic_entropy": 8.682042121887207,
          "acoustic_entropy_side": 8.468067169189453,
          "hz": 1080.2004963696966
        },
        {
          "acoustic_entropy": 9.233749389648438,
          "acoustic_entropy_side": 8.468067169189453,
          "hz": 1237.8529382007157
        },
        {
          "acoustic_entropy": 8.543054580688477,
          "acoustic_entropy_side": 8.468067169189453,
          "hz": 1409.4668930556702
        },
        {
          "acoustic_entropy": 8.45130443572998,
          "acoustic_entropy_side": 8.468067169189453,
          "hz": 1596.2787759475705
        },
        {
          "acoustic_entropy": 8.576849937438965,
          "acoustic_entropy_side": 8.468067169189453,
          "hz": 1799.6344973346393
        },
        {
          "acoustic_entropy": 8.635421752929688,
          "acoustic_entropy_side": 8.468067169189453,
          "hz": 2020.9991599069049
        },
        {
          "acoustic_entropy": 8.280011177062988,
          "acoustic_entropy_side": 8.468067169189453,
          "hz": 2261.9676141086993
        },
        {
          "acoustic_entropy": 8.319608688354492,
          "acoustic_entropy_side": 8.468067169189453,
          "hz": 2524.2759484456974
        },
        {
          "acoustic_entropy": 8.422956466674805,
          "acoustic_entropy_side": 8.468067169189453,
          "hz": 2809.813997359896
        },
        {
          "acoustic_entropy": 8.372425079345703,
          "acoustic_entropy_side": 8.468067169189453,
          "hz": 3120.6389567871424
        },
        {
          "acoustic_entropy": 8.353438377380371,
          "acoustic_entropy_side": 8.468067169189453,
          "hz": 3458.990205492291
        },
        {
          "acoustic_entropy": 8.387060165405273,
          "acoustic_entropy_side": 8.468067169189453,
          "hz": 3827.305438964164
        },
        {
          "acoustic_entropy": 8.395947456359863,
          "acoustic_entropy_side": 8.468067169189453,
          "hz": 4228.238232109126
        },
        {
          "acoustic_entropy": 8.48476791381836,
          "acoustic_entropy_side": 8.468067169189453,
          "hz": 4664.6771572759235
        },
        {
          "acoustic_entropy": 8.147807121276855,
          "acoustic_entropy_side": 8.468067169189453,
          "hz": 5139.766595350093
        },
        {
          "acoustic_entropy": 8.338386535644531,
          "acoustic_entropy_side": 8.468067169189453,
          "hz": 5656.929389854203
        },
        {
          "acoustic_entropy": 8.43604850769043,
          "acoustic_entropy_side": 8.468067169189453,
          "hz": 6219.891507268283
        },
        {
          "acoustic_entropy": 8.391924858093262,
          "acoustic_entropy_side": 8.468067169189453,
          "hz": 6832.70888123896
        },
        {
          "acoustic_entropy": 8.433984756469727,
          "acoustic_entropy_side": 8.468067169189453,
          "hz": 7499.796634079867
        },
        {
          "acoustic_entropy": 8.442741394042969,
          "acoustic_entropy_side": 8.468067169189453,
          "hz": 8225.96088609342
        },
        {
          "acoustic_entropy": 8.46419906616211,
          "acoustic_entropy_side": 8.468067169189453,
          "hz": 9016.43338188839
        },
        {
          "acoustic_entropy": 8.390018463134766,
          "acoustic_entropy_side": 8.468067169189453,
          "hz": 9876.909183162974
        },
        {
          "acoustic_entropy": 8.411863327026367,
          "acoustic_entropy_side": 8.468067169189453,
          "hz": 10813.587699516042
        },
        {
          "acoustic_entropy": 8.424351692199707,
          "acoustic_entropy_side": 8.468067169189453,
          "hz": 11833.21735289826
        },
        {
          "acoustic_entropy": 8.437463760375977,
          "acoustic_entropy_side": 8.468067169189453,
          "hz": 12943.144197493959
        },
        {
          "acoustic_entropy": 8.451488494873047,
          "acoustic_entropy_side": 8.468067169189453,
          "hz": 14151.364845322005
        },
        {
          "acoustic_entropy": 8.443124771118164,
          "acoustic_entropy_side": 8.468067169189453,
          "hz": 15466.58407886509
        },
        {
          "acoustic_entropy": 8.466203689575195,
          "acoustic_entropy_side": 8.468067169189453,
          "hz": 16898.27756580493
        },
        {
          "acoustic_entropy": 8.468067169189453,
          "acoustic_entropy_side": 8.468067169189453,
          "hz": 18456.760127700032
        },
        {
          "acoustic_entropy": 8.468067169189453,
          "acoustic_entropy_side": 8.468067169189453,
          "hz": 20153.260054456492
        },
        {
          "acoustic_entropy": 8.468067169189453,
          "acoustic_entropy_side": 8.468067169189453,
          "hz": 22000.00000000001
        }
      ],
      "diff_acoustic_entropy": 7.6610260009765625,
      "sn": 6
    },
    {
      "acoustic_entropy": 10.663457870483398,
      "acoustic_entropy_mono": 10.663457870483398,
      "band_eliminated_acoustic_entropies": [
        {
          "acoustic_entropy": 10.659032821655273,
          "acoustic_entropy_side": 10.663457870483398,
          "hz": 129.47220167065723
        },
        {
          "acoustic_entropy": 10.541482925415039,
          "acoustic_entropy_side": 10.663457870483398,
          "hz": 202.92927478742237
        },
        {
          "acoustic_entropy": 10.403562545776367,
          "acoustic_entropy_side": 10.663457870483398,
          "hz": 282.89161906338205
        },
        {
          "acoustic_entropy": 10.41120433807373,
          "acoustic_entropy_side": 10.663457870483398,
          "hz": 369.9353335868758
        },
        {
          "acoustic_entropy": 10.61989974975586,
          "acoustic_entropy_side": 10.663457870483398,
          "hz": 464.6875360973435
        },
        {
          "acoustic_entropy": 10.681611061096191,
          "acoustic_entropy_side": 10.663457870483398,
          "hz": 567.8308811364784
        },
        {
          "acoustic_entropy": 10.619746208190918,
          "acoustic_entropy_side": 10.663457870483398,
          "hz": 680.1084783214808
        },
        {
          "acoustic_entropy": 10.680264472961426,
          "acoustic_entropy_side": 10.663457870483398,
          "hz": 802.3292461747484
        },
        {
          "acoustic_entropy": 10.761838912963867,
          "acoustic_entropy_side": 10.663457870483398,
          "hz": 935.3737400823702
        },
        {
          "acoustic_entropy": 11.252352714538574,
          "acoustic_entropy_side": 10.663457870483398,
          "hz": 1080.2004963696966
        },
        {
          "acoustic_entropy": 10.939226150512695,
          "acoustic_entropy_side": 10.663457870483398,
          "hz": 1237.8529382007157
        },
        {
          "acoustic_entropy": 11.026695251464844,
          "acoustic_entropy_side": 10.663457870483398,
          "hz": 1409.4668930556702
        },
        {
          "acoustic_entropy": 11.093779563903809,
          "acoustic_entropy_side": 10.663457870483398,
          "hz": 1596.2787759475705
        },
        {
          "acoustic_entropy": 10.870868682861328,
          "acoustic_entropy_side": 10.663457870483398,
          "hz": 1799.6344973346393
        },
        {
          "acoustic_entropy": 11.621796607971191,
          "acoustic_entropy_side": 10.663457870483398,
          "hz": 2020.9991599069049
        },
        {
          "acoustic_entropy": 10.9089937210083,
          "acoustic_entropy_side": 10.663457870483398,
          "hz": 2261.9676141086993
        },
        {
          "acoustic_entropy": 10.718530654907227,
          "acoustic_entropy_side": 10.663457870483398,
          "hz": 2524.2759484456974
        },
        {
          "acoustic_entropy": 10.627796173095703,
          "acoustic_entropy_side": 10.663457870483398,
          "hz": 2809.813997359896
        },
        {
          "acoustic_entropy": 10.541316032409668,
          "acoustic_entropy_side": 10.663457870483398,
          "hz": 3120.6389567871424
        },
        {
          "acoustic_entropy": 10.54273509979248,
          "acoustic_entropy_side": 10.663457870483398,
          "hz": 3458.990205492291
        },
        {
          "acoustic_entropy": 10.6068754196167,
          "acoustic_entropy_side": 10.663457870483398,
          "hz": 3827.305438964164
        },
        {
          "acoustic_entropy": 10.437982559204102,
          "acoustic_entropy_side": 10.663457870483398,
          "hz": 4228.238232109126
        },
        {
          "acoustic_entropy": 10.643247604370117,
          "acoustic_entropy_side": 10.663457870483398,
          "hz": 4664.6771572759235
        },
        {
          "acoustic_entropy": 11.189933776855469,
          "acoustic_entropy_side": 10.663457870483398,
          "hz": 5139.766595350093
        },
        {
          "acoustic_entropy": 10.148043632507324,
          "acoustic_entropy_side": 10.663457870483398,
          "hz": 5656.929389854203
        },
        {
          "acoustic_entropy": 10.747051239013672,
          "acoustic_entropy_side": 10.663457870483398,
          "hz": 6219.891507268283
        },
        {
          "acoustic_entropy": 10.54482650756836,
          "acoustic_entropy_side": 10.663457870483398,
          "hz": 6832.70888123896
        },
        {
          "acoustic_entropy": 10.615011215209961,
          "acoustic_entropy_side": 10.663457870483398,
          "hz": 7499.796634079867
        },
        {
          "acoustic_entropy": 10.603144645690918,
          "acoustic_entropy_side": 10.663457870483398,
          "hz": 8225.96088609342
        },
        {
          "acoustic_entropy": 10.68522834777832,
          "acoustic_entropy_side": 10.663457870483398,
          "hz": 9016.43338188839
        },
        {
          "acoustic_entropy": 10.646629333496094,
          "acoustic_entropy_side": 10.663457870483398,
          "hz": 9876.909183162974
        },
        {
          "acoustic_entropy": 10.666760444641113,
          "acoustic_entropy_side": 10.663457870483398,
          "hz": 10813.587699516042
        },
        {
          "acoustic_entropy": 10.631064414978027,
          "acoustic_entropy_side": 10.663457870483398,
          "hz": 11833.21735289826
        },
        {
          "acoustic_entropy": 10.618627548217773,
          "acoustic_entropy_side": 10.663457870483398,
          "hz": 12943.144197493959
        },
        {
          "acoustic_entropy": 10.628395080566406,
          "acoustic_entropy_side": 10.663457870483398,
          "hz": 14151.364845322005
        },
        {
          "acoustic_entropy": 10.596050262451172,
          "acoustic_entropy_side": 10.663457870483398,
          "hz": 15466.58407886509
        },
        {
          "acoustic_entropy": 10.644902229309082,
          "acoustic_entropy_side": 10.663457870483398,
          "hz": 16898.27756580493
        },
        {
          "acoustic_entropy": 10.663457870483398,
          "acoustic_entropy_side": 10.663457870483398,
          "hz": 18456.760127700032
        },
        {
          "acoustic_entropy": 10.663457870483398,
          "acoustic_entropy_side": 10.663457870483398,
          "hz": 20153.260054456492
        },
        {
          "acoustic_entropy": 10.663457870483398,
          "acoustic_entropy_side": 10.663457870483398,
          "hz": 22000.00000000001
        }
      ],
      "diff_acoustic_entropy": 9.96068286895752,
      "sn": 12
    },
    {
      "acoustic_entropy": 14.201996803283691,
      "acoustic_entropy_mono": 14.201996803283691,
      "band_eliminated_acoustic_entropies": [
        {
          "acoustic_entropy": 14.192151069641113,
          "acoustic_entropy_side": 14.201996803283691,
          "hz": 129.47220167065723
        },
        {
          "acoustic_entropy": 14.080361366271973,
          "acoustic_entropy_side": 14.201996803283691,
          "hz": 202.92927478742237
        },
        {
          "acoustic_entropy": 14.164355278015137,
          "acoustic_entropy_side": 14.201996803283691,
          "hz": 282.89161906338205
        },
        {
          "acoustic_entropy": 14.16559886932373,
          "acoustic_entropy_side": 14.201996803283691,
          "hz": 369.9353335868758
        },
        {
          "acoustic_entropy": 14.2391939163208,
          "acoustic_entropy_side": 14.201996803283691,
          "hz": 464.6875360973435
        },
        {
          "acoustic_entropy": 14.365306854248047,
          "acoustic_entropy_side": 14.201996803283691,
          "hz": 567.8308811364784
        },
        {
          "acoustic_entropy": 14.394143104553223,
          "acoustic_entropy_side": 14.201996803283691,
          "hz": 680.1084783214808
        },
        {
          "acoustic_entropy": 14.323827743530273,
          "acoustic_entropy_side": 14.201996803283691,
          "hz": 802.3292461747484
        },
        {
          "acoustic_entropy": 14.435774803161621,
          "acoustic_entropy_side": 14.201996803283691,
          "hz": 935.3737400823702
        },
        {
          "acoustic_entropy": 14.190956115722656,
          "acoustic_entropy_side": 14.201996803283691,
          "hz": 1080.2004963696966
        },
        {
          "acoustic_entropy": 13.798697471618652,
          "acoustic_entropy_side": 14.201996803283691,
          "hz": 1237.8529382007157
        },
        {
          "acoustic_entropy": 14.582728385925293,
          "acoustic_entropy_side": 14.201996803283691,
          "hz": 1409.4668930556702
        },
        {
          "acoustic_entropy": 13.955057144165039,
          "acoustic_entropy_side": 14.201996803283691,
          "hz": 1596.2787759475705
        },
        {
          "acoustic_entropy": 14.39571475982666,
          "acoustic_entropy_side": 14.201996803283691,
          "hz": 1799.6344973346393
        },
        {
          "acoustic_entropy": 14.411834716796875,
          "acoustic_entropy_side": 14.201996803283691,
          "hz": 2020.9991599069049
        },
        {
          "acoustic_entropy": 14.591200828552246,
          "acoustic_entropy_side": 14.201996803283691,
          "hz": 2261.9676141086993
        },
        {
          "acoustic_entropy": 14.144316673278809,
          "acoustic_entropy_side": 14.201996803283691,
          "hz": 2524.2759484456974
        },
        {
          "acoustic_entropy": 14.01311206817627,
          "acoustic_entropy_side": 14.201996803283691,
          "hz": 2809.813997359896
        },
        {
          "acoustic_entropy": 14.239666938781738,
          "acoustic_entropy_side": 14.201996803283691,
          "hz": 3120.6389567871424
        },
        {
          "acoustic_entropy": 14.171229362487793,
          "acoustic_entropy_side": 14.201996803283691,
          "hz": 3458.990205492291
        },
        {
          "acoustic_entropy": 14.206122398376465,
          "acoustic_entropy_side": 14.201996803283691,
          "hz": 3827.305438964164
        },
        {
          "acoustic_entropy": 14.334403038024902,
          "acoustic_entropy_side": 14.201996803283691,
          "hz": 4228.238232109126
        },
        {
          "acoustic_entropy": 14.031840324401855,
          "acoustic_entropy_side": 14.201996803283691,
          "hz": 4664.6771572759235
        },
        {
          "acoustic_entropy": 14.544678688049316,
          "acoustic_entropy_side": 14.201996803283691,
          "hz": 5139.766595350093
        },
        {
          "acoustic_entropy": 14.13505744934082,
          "acoustic_entropy_side": 14.201996803283691,
          "hz": 5656.929389854203
        },
        {
          "acoustic_entropy": 14.255363464355469,
          "acoustic_entropy_side": 14.201996803283691,
          "hz": 6219.891507268283
        },
        {
          "acoustic_entropy": 14.095144271850586,
          "acoustic_entropy_side": 14.201996803283691,
          "hz": 6832.70888123896
        },
        {
          "acoustic_entropy": 14.129219055175781,
          "acoustic_entropy_side": 14.201996803283691,
          "hz": 7499.796634079867
        },
        {
          "acoustic_entropy": 14.112914085388184,
          "acoustic_entropy_side": 14.201996803283691,
          "hz": 8225.96088609342
        },
        {
          "acoustic_entropy": 14.147574424743652,
          "acoustic_entropy_side": 14.201996803283691,
          "hz": 9016.43338188839
        },
        {
          "acoustic_entropy": 14.022942543029785,
          "acoustic_entropy_side": 14.201996803283691,
          "hz": 9876.909183162974
        },
        {
          "acoustic_entropy": 14.278656005859375,
          "acoustic_entropy_side": 14.201996803283691,
          "hz": 10813.587699516042
        },
        {
          "acoustic_entropy": 14.251521110534668,
          "acoustic_entropy_side": 14.201996803283691,
          "hz": 11833.21735289826
        },
        {
          "acoustic_entropy": 14.1149320602417,
          "acoustic_entropy_side": 14.201996803283691,
          "hz": 12943.144197493959
        },
        {
          "acoustic_entropy": 14.254432678222656,
          "acoustic_entropy_side": 14.201996803283691,
          "hz": 14151.364845322005
        },
        {
          "acoustic_entropy": 14.217863082885742,
          "acoustic_entropy_side": 14.201996803283691,
          "hz": 15466.58407886509
        },
        {
          "acoustic_entropy": 14.168959617614746,
          "acoustic_entropy_side": 14.201996803283691,
          "hz": 16898.27756580493
        },
        {
          "acoustic_entropy": 14.201994895935059,
          "acoustic_entropy_side": 14.201996803283691,
          "hz": 18456.760127700032
        },
        {
          "acoustic_entropy": 14.201996803283691,
          "acoustic_entropy_side": 14.201996803283691,
          "hz": 20153.260054456492
        },
        {
          "acoustic_entropy": 14.201996803283691,
          "acoustic_entropy_side": 14.201996803283691,
          "hz": 22000.00000000001
        }
      ],
      "diff_acoustic_entropy": 13.237320899963379,
      "sn": 24
    },
    {
      "acoustic_entropy": 16.891307830810547,
      "acoustic_entropy_mono": 16.891307830810547,
      "band_eliminated_acoustic_entropies": [
        {
          "acoustic_entropy": 16.900732040405273,
          "acoustic_entropy_side": 16.891307830810547,
          "hz": 129.47220167065723
        },
        {
          "acoustic_entropy": 16.895788192749023,
          "acoustic_entropy_side": 16.891307830810547,
          "hz": 202.92927478742237
        },
        {
          "acoustic_entropy": 16.82408905029297,
          "acoustic_entropy_side": 16.891307830810547,
          "hz": 282.89161906338205
        },
        {
          "acoustic_entropy": 17.036693572998047,
          "acoustic_entropy_side": 16.891307830810547,
          "hz": 369.9353335868758
        },
        {
          "acoustic_entropy": 16.95551872253418,
          "acoustic_entropy_side": 16.891307830810547,
          "hz": 464.6875360973435
        },
        {
          "acoustic_entropy": 16.770872116088867,
          "acoustic_entropy_side": 16.891307830810547,
          "hz": 567.8308811364784
        },
        {
          "acoustic_entropy": 16.797374725341797,
          "acoustic_entropy_side": 16.891307830810547,
          "hz": 680.1084783214808
        },
        {
          "acoustic_entropy": 16.958669662475586,
          "acoustic_entropy_side": 16.891307830810547,
          "hz": 802.3292461747484
        },
        {
          "acoustic_entropy": 16.962358474731445,
          "acoustic_entropy_side": 16.891307830810547,
          "hz": 935.3737400823702
        },
        {
          "acoustic_entropy": 16.870161056518555,
          "acoustic_entropy_side": 16.891307830810547,
          "hz": 1080.2004963696966
        },
        {
          "acoustic_entropy": 16.978191375732422,
          "acoustic_entropy_side": 16.891307830810547,
          "hz": 1237.8529382007157
        },
        {
          "acoustic_entropy": 16.535110473632812,
          "acoustic_entropy_side": 16.891307830810547,
          "hz": 1409.4668930556702
        },
        {
          "acoustic_entropy": 16.9196720123291,
          "acoustic_entropy_side": 16.891307830810547,
          "hz": 1596.2787759475705
        },
        {
          "acoustic_entropy": 16.725984573364258,
          "acoustic_entropy_side": 16.891307830810547,
          "hz": 1799.6344973346393
        },
        {
          "acoustic_entropy": 16.56178092956543,
          "acoustic_entropy_side": 16.891307830810547,
          "hz": 2020.9991599069049
        },
        {
          "acoustic_entropy": 16.664613723754883,
          "acoustic_entropy_side": 16.891307830810547,
          "hz": 2261.9676141086993
        },
        {
          "acoustic_entropy": 16.812881469726562,
          "acoustic_entropy_side": 16.891307830810547,
          "hz": 2524.2759484456974
        },
        {
          "acoustic_entropy": 16.908645629882812,
          "acoustic_entropy_side": 16.891307830810547,
          "hz": 2809.813997359896
        },
        {
          "acoustic_entropy": 16.699132919311523,
          "acoustic_entropy_side": 16.891307830810547,
          "hz": 3120.6389567871424
        },
        {
          "acoustic_entropy": 16.80535316467285,
          "acoustic_entropy_side": 16.891307830810547,
          "hz": 3458.990205492291
        },
        {
          "acoustic_entropy": 16.673498153686523,
          "acoustic_entropy_side": 16.891307830810547,
          "hz": 3827.305438964164
        },
        {
          "acoustic_entropy": 16.804197311401367,
          "acoustic_entropy_side": 16.891307830810547,
          "hz": 4228.238232109126
        },
        {
          "acoustic_entropy": 16.897552490234375,
          "acoustic_entropy_side": 16.891307830810547,
          "hz": 4664.6771572759235
        },
        {
          "acoustic_entropy": 15.87031078338623,
          "acoustic_entropy_side": 16.891307830810547,
          "hz": 5139.766595350093
        },
        {
          "acoustic_entropy": 16.94498062133789,
          "acoustic_entropy_side": 16.891307830810547,
          "hz": 5656.929389854203
        },
        {
          "acoustic_entropy": 17.016220092773438,
          "acoustic_entropy_side": 16.891307830810547,
          "hz": 6219.891507268283
        },
        {
          "acoustic_entropy": 16.726022720336914,
          "acoustic_entropy_side": 16.891307830810547,
          "hz": 6832.70888123896
        },
        {
          "acoustic_entropy": 16.81155014038086,
          "acoustic_entropy_side": 16.891307830810547,
          "hz": 7499.796634079867
        },
        {
          "acoustic_entropy": 16.71575355529785,
          "acoustic_entropy_side": 16.891307830810547,
          "hz": 8225.96088609342
        },
        {
          "acoustic_entropy": 16.919370651245117,
          "acoustic_entropy_side": 16.891307830810547,
          "hz": 9016.43338188839
        },
        {
          "acoustic_entropy": 16.616018295288086,
          "acoustic_entropy_side": 16.891307830810547,
          "hz": 9876.909183162974
        },
        {
          "acoustic_entropy": 16.898775100708008,
          "acoustic_entropy_side": 16.891307830810547,
          "hz": 10813.587699516042
        },
        {
          "acoustic_entropy": 17.019187927246094,
          "acoustic_entropy_side": 16.891307830810547,
          "hz": 11833.21735289826
        },
        {
          "acoustic_entropy": 16.756193161010742,
          "acoustic_entropy_side": 16.891307830810547,
          "hz": 12943.144197493959
        },
        {
          "acoustic_entropy": 16.98794174194336,
          "acoustic_entropy_side": 16.891307830810547,
          "hz": 14151.364845322005
        },
        {
          "acoustic_entropy": 16.759836196899414,
          "acoustic_entropy_side": 16.891307830810547,
          "hz": 15466.58407886509
        },
        {
          "acoustic_entropy": 16.878154754638672,
          "acoustic_entropy_side": 16.891307830810547,
          "hz": 16898.27756580493
        },
        {
          "acoustic_entropy": 16.891338348388672,
          "acoustic_entropy_side": 16.891307830810547,
          "hz": 18456.760127700032
        },
        {
          "acoustic_entropy": 16.890846252441406,
          "acoustic_entropy_side": 16.891307830810547,
          "hz": 20153.260054456492
        },
        {
          "acoustic_entropy": 16.891817092895508,
          "acoustic_entropy_side": 16.891307830810547,
          "hz": 22000.00000000001
        }
      ],
      "diff_acoustic_entropy": 15.220054626464844,
      "sn": 72
    }
  ],
  "mastering3_ear_damage": 62.75537872314453,
  "mastering3_loudness": 50.36808395385742,
  "peak": -3.8842623233795166,
  "rms": -30.011852264404297,
  "sample_rate": 44100,
  "sections": 1,
  "seekable": 1,
  "sharpness": 10.47307014465332,
  "space": -46.09517288208008,
  "true_peak": -3.8842623233795166,
  "version": "34a0772fe867fa2d9918243d16da8e990c214896",
  "youtube_loudness": -22.013816833496094
}